<?xml version="1.0" encoding="UTF-8"?>
<billStatus>
  <bill>
    <billNumber>5074</billNumber>
    <createDate>2018-02-21T03:10:58Z</createDate>
    <updateDate>2021-07-10T20:10:51Z</updateDate>
    <originChamber>House</originChamber>
    <billType>HR</billType>
    <introducedDate>2018-02-20</introducedDate>
    <congress>115</congress>
    <constitutionalAuthorityStatementText><![CDATA[<pre>[Congressional Record Volume 164, Number 32 (Tuesday, February 20, 2018)]From the Congressional Record Online through the Government Publishing Office [<a href='http://www.gpo.gov'>www.gpo.gov</a>]By Mr. McCAUL:H.R. 5074.Congress has the power to enact this legislation pursuantto the following:Article I, Section 8, Clause 18: To make all Laws whichshall be necessary and proper for carrying into Execution theforegoing Powers, and all other Powers vested by thisConstitution in the Government of the United States, or inany Department or Officer thereof.[Page H1221]</pre>]]></constitutionalAuthorityStatementText>
    <recordedVotes />
    <committees>
      <billCommittees>
        <item>
          <systemCode>ssga00</systemCode>
          <name>Homeland Security and Governmental Affairs Committee</name>
          <chamber>Senate</chamber>
          <type>Standing</type>
          <subcommittees />
          <activities>
            <item>
              <name>Referred to</name>
              <date>2018-03-20T15:19:14Z</date>
            </item>
          </activities>
        </item>
        <item>
          <systemCode>hshm00</systemCode>
          <name>Homeland Security Committee</name>
          <chamber>House</chamber>
          <type>Standing</type>
          <subcommittees>
            <item>
              <systemCode>hshm08</systemCode>
              <name>Cybersecurity, Infrastructure Protection, and Innovation Subcommittee</name>
              <activities>
                <item>
                  <name>Discharged from</name>
                  <date>2018-03-07T22:22:41Z</date>
                </item>
                <item>
                  <name>Referred to</name>
                  <date>2018-02-28T20:38:27Z</date>
                </item>
              </activities>
            </item>
          </subcommittees>
          <activities>
            <item>
              <name>Reported by</name>
              <date>2018-03-19T16:49:56Z</date>
            </item>
            <item>
              <name>Markup by</name>
              <date>2018-03-07T22:22:56Z</date>
            </item>
            <item>
              <name>Referred to</name>
              <date>2018-02-20T15:26:40Z</date>
            </item>
          </activities>
        </item>
      </billCommittees>
    </committees>
    <committeeReports>
      <committeeReport>
        <citation>H. Rept. 115-607</citation>
      </committeeReport>
    </committeeReports>
    <relatedBills>
      <item>
        <latestTitle>DHS Cyber Incident Response Teams Act of 2018</latestTitle>
        <congress>115</congress>
        <number>3309</number>
        <type>S</type>
        <latestAction>
          <actionDate>2018-12-04</actionDate>
          <text>Placed on Senate Legislative Calendar under General Orders. Calendar No. 716.</text>
        </latestAction>
        <relationshipDetails>
          <item>
            <type>Related bill</type>
            <identifiedBy>CRS</identifiedBy>
          </item>
          <item>
            <type>Related bill</type>
            <identifiedBy>House</identifiedBy>
          </item>
        </relationshipDetails>
      </item>
    </relatedBills>
    <actions>
      <item>
        <actionDate>2018-03-20</actionDate>
        <committees>
          <item>
            <systemCode>ssga00</systemCode>
            <name>Homeland Security and Governmental Affairs Committee</name>
          </item>
        </committees>
        <links />
        <sourceSystem>
          <code>0</code>
          <name>Senate</name>
        </sourceSystem>
        <text>Received in the Senate and Read twice and referred to the Committee on Homeland Security and Governmental Affairs.</text>
        <type>IntroReferral</type>
      </item>
      <item>
        <actionDate>2018-03-19</actionDate>
        <actionTime>16:14:43</actionTime>
        <links />
        <text>Motion to reconsider laid on the table Agreed to without objection.</text>
        <type>Floor</type>
        <actionCode>H38310</actionCode>
        <sourceSystem>
          <code>2</code>
          <name>House floor actions</name>
        </sourceSystem>
        <committees />
      </item>
      <item>
        <actionDate>2018-03-19</actionDate>
        <actionTime>16:14:41</actionTime>
        <links />
        <text>On motion to suspend the rules and pass the bill, as amended Agreed to by voice vote. (text: CR H1661)</text>
        <type>Floor</type>
        <actionCode>H37300</actionCode>
        <sourceSystem>
          <code>2</code>
          <name>House floor actions</name>
        </sourceSystem>
        <committees />
      </item>
      <item>
        <actionDate>2018-03-19</actionDate>
        <actionTime>16:14:41</actionTime>
        <links />
        <text>Passed/agreed to in House: On motion to suspend the rules and pass the bill, as amended Agreed to by voice vote.(text: CR H1661)</text>
        <type>Floor</type>
        <actionCode>8000</actionCode>
        <sourceSystem>
          <code>9</code>
          <name>Library of Congress</name>
        </sourceSystem>
        <committees />
      </item>
      <item>
        <actionDate>2018-03-19</actionDate>
        <actionTime>16:03:38</actionTime>
        <links />
        <text>DEBATE - The House proceeded with forty minutes of debate on H.R. 5074.</text>
        <type>Floor</type>
        <actionCode>H8D000</actionCode>
        <sourceSystem>
          <code>2</code>
          <name>House floor actions</name>
        </sourceSystem>
        <committees />
      </item>
      <item>
        <actionDate>2018-03-19</actionDate>
        <actionTime>16:03:37</actionTime>
        <links />
        <text>Considered under suspension of the rules. (consideration: CR H1661-1663)</text>
        <type>Floor</type>
        <actionCode>H30000</actionCode>
        <sourceSystem>
          <code>2</code>
          <name>House floor actions</name>
        </sourceSystem>
        <committees />
      </item>
      <item>
        <actionDate>2018-03-19</actionDate>
        <actionTime>16:03:25</actionTime>
        <links />
        <text>Mr. McCaul moved to suspend the rules and pass the bill, as amended.</text>
        <type>Floor</type>
        <actionCode>H30300</actionCode>
        <sourceSystem>
          <code>2</code>
          <name>House floor actions</name>
        </sourceSystem>
        <committees />
      </item>
      <item>
        <actionDate>2018-03-19</actionDate>
        <links />
        <text>Placed on the Union Calendar, Calendar No. 463.</text>
        <type>Calendars</type>
        <actionCode>H12410</actionCode>
        <sourceSystem>
          <code>2</code>
          <name>House floor actions</name>
        </sourceSystem>
        <committees />
      </item>
      <item>
        <actionDate>2018-03-19</actionDate>
        <links />
        <text>Reported by the Committee on Homeland Security. H. Rept. 115-607.</text>
        <type>Committee</type>
        <actionCode>H12200</actionCode>
        <sourceSystem>
          <code>2</code>
          <name>House floor actions</name>
        </sourceSystem>
        <committees>
          <item>
            <systemCode>hshm00</systemCode>
            <name>Homeland Security Committee</name>
          </item>
        </committees>
      </item>
      <item>
        <actionDate>2018-03-19</actionDate>
        <links />
        <text>Reported by the Committee on Homeland Security. H. Rept. 115-607.</text>
        <type>Committee</type>
        <actionCode>5000</actionCode>
        <sourceSystem>
          <code>9</code>
          <name>Library of Congress</name>
        </sourceSystem>
        <committees>
          <item>
            <systemCode>hshm00</systemCode>
            <name>Homeland Security Committee</name>
          </item>
        </committees>
      </item>
      <item>
        <actionDate>2018-03-07</actionDate>
        <committees>
          <item>
            <systemCode>hshm00</systemCode>
            <name>Homeland Security Committee</name>
          </item>
        </committees>
        <links />
        <sourceSystem>
          <code>1</code>
          <name>House committee actions</name>
        </sourceSystem>
        <text>Ordered to be Reported by Unanimous Consent.</text>
        <type>Committee</type>
      </item>
      <item>
        <actionDate>2018-03-07</actionDate>
        <committees>
          <item>
            <systemCode>hshm00</systemCode>
            <name>Homeland Security Committee</name>
          </item>
        </committees>
        <links />
        <sourceSystem>
          <code>1</code>
          <name>House committee actions</name>
        </sourceSystem>
        <text>Committee Consideration and Mark-up Session Held.</text>
        <type>Committee</type>
      </item>
      <item>
        <actionDate>2018-03-07</actionDate>
        <committees>
          <item>
            <systemCode>hshm00</systemCode>
            <name>Homeland Security Committee</name>
          </item>
        </committees>
        <links />
        <sourceSystem>
          <code>1</code>
          <name>House committee actions</name>
        </sourceSystem>
        <text>Subcommittee on Cybersecurity and Infrastructure Protection Discharged.</text>
        <type>Committee</type>
      </item>
      <item>
        <actionDate>2018-02-28</actionDate>
        <committees>
          <item>
            <systemCode>hshm08</systemCode>
            <name>Cybersecurity, Infrastructure Protection, and Innovation Subcommittee</name>
          </item>
        </committees>
        <links />
        <sourceSystem>
          <code>1</code>
          <name>House committee actions</name>
        </sourceSystem>
        <text>Referred to the Subcommittee on Cybersecurity and Infrastructure Protection.</text>
        <type>Committee</type>
      </item>
      <item>
        <actionDate>2018-02-20</actionDate>
        <links />
        <text>Referred to the House Committee on Homeland Security.</text>
        <type>IntroReferral</type>
        <actionCode>H11100</actionCode>
        <sourceSystem>
          <code>2</code>
          <name>House floor actions</name>
        </sourceSystem>
        <committees>
          <item>
            <systemCode>hshm00</systemCode>
            <name>Homeland Security Committee</name>
          </item>
        </committees>
      </item>
      <item>
        <actionDate>2018-02-20</actionDate>
        <links />
        <text>Introduced in House</text>
        <type>IntroReferral</type>
        <actionCode>Intro-H</actionCode>
        <sourceSystem>
          <code>9</code>
          <name>Library of Congress</name>
        </sourceSystem>
        <committees />
      </item>
      <item>
        <actionDate>2018-02-20</actionDate>
        <links />
        <text>Introduced in House</text>
        <type>IntroReferral</type>
        <actionCode>1000</actionCode>
        <sourceSystem>
          <code>9</code>
          <name>Library of Congress</name>
        </sourceSystem>
        <committees />
      </item>
      <actionTypeCounts>
        <referredToCommittee>1</referredToCommittee>
        <motionToReconsiderResults>1</motionToReconsiderResults>
        <finalPassageUnderSuspensionOfTheRulesResults>1</finalPassageUnderSuspensionOfTheRulesResults>
        <passedAgreedToInHouse>1</passedAgreedToInHouse>
        <generalDebate>1</generalDebate>
        <considerationByHouse>1</considerationByHouse>
        <motionMadeToSuspendTheRules>1</motionMadeToSuspendTheRules>
        <unionCalendarAssignment>1</unionCalendarAssignment>
        <committeeReportOfABill>1</committeeReportOfABill>
        <reportedToHouse>1</reportedToHouse>
        <orderedToBeReported>1</orderedToBeReported>
        <committeeConsiderationMarkUp>1</committeeConsiderationMarkUp>
        <subcommitteeDischarged>1</subcommitteeDischarged>
        <placeholderTextForH>1</placeholderTextForH>
        <billReferrals>1</billReferrals>
        <introducedInTheHouse>1</introducedInTheHouse>
        <introducedInHouse>1</introducedInHouse>
      </actionTypeCounts>
      <actionByCounts>
        <senate>1</senate>
        <houseOfRepresentatives>16</houseOfRepresentatives>
      </actionByCounts>
    </actions>
    <sponsors>
      <item>
        <bioguideId>M001157</bioguideId>
        <fullName>Rep. McCaul, Michael T. [R-TX-10]</fullName>
        <firstName>Michael</firstName>
        <middleName>T.</middleName>
        <lastName>McCaul</lastName>
        <party>R</party>
        <state>TX</state>
        <identifiers>
          <lisID>1804</lisID>
          <bioguideId>M001157</bioguideId>
          <gpoId>8166</gpoId>
        </identifiers>
        <district>10</district>
        <byRequestType />
      </item>
    </sponsors>
    <cosponsors>
      <item>
        <bioguideId>R000601</bioguideId>
        <fullName>Rep. Ratcliffe, John [R-TX-4]</fullName>
        <firstName>John</firstName>
        <middleName />
        <lastName>Ratcliffe</lastName>
        <party>R</party>
        <state>TX</state>
        <identifiers>
          <lisID>2268</lisID>
          <bioguideId>R000601</bioguideId>
          <gpoId />
        </identifiers>
        <district>4</district>
        <sponsorshipDate>2018-02-20</sponsorshipDate>
        <isOriginalCosponsor>True</isOriginalCosponsor>
        <sponsorshipWithdrawnDate />
      </item>
      <item>
        <bioguideId>D000625</bioguideId>
        <fullName>Rep. Donovan, Daniel M., Jr. [R-NY-11]</fullName>
        <firstName>Daniel</firstName>
        <middleName>M.</middleName>
        <lastName>Donovan</lastName>
        <party>R</party>
        <state>NY</state>
        <identifiers>
          <lisID>2293</lisID>
          <bioguideId>D000625</bioguideId>
          <gpoId />
        </identifiers>
        <district>11</district>
        <sponsorshipDate>2018-02-20</sponsorshipDate>
        <isOriginalCosponsor>True</isOriginalCosponsor>
        <sponsorshipWithdrawnDate />
      </item>
      <item>
        <bioguideId>G000579</bioguideId>
        <fullName>Rep. Gallagher, Mike [R-WI-8]</fullName>
        <firstName>Mike</firstName>
        <middleName />
        <lastName>Gallagher</lastName>
        <party>R</party>
        <state>WI</state>
        <identifiers>
          <lisID>2355</lisID>
          <bioguideId>G000579</bioguideId>
          <gpoId />
        </identifiers>
        <district>8</district>
        <sponsorshipDate>2018-02-20</sponsorshipDate>
        <isOriginalCosponsor>True</isOriginalCosponsor>
        <sponsorshipWithdrawnDate />
      </item>
      <item>
        <bioguideId>F000466</bioguideId>
        <fullName>Rep. Fitzpatrick, Brian K. [R-PA-8]</fullName>
        <firstName>Brian</firstName>
        <middleName>K.</middleName>
        <lastName>Fitzpatrick</lastName>
        <party>R</party>
        <state>PA</state>
        <identifiers>
          <lisID>2345</lisID>
          <bioguideId>F000466</bioguideId>
          <gpoId />
        </identifiers>
        <district>8</district>
        <sponsorshipDate>2018-02-20</sponsorshipDate>
        <isOriginalCosponsor>True</isOriginalCosponsor>
        <sponsorshipWithdrawnDate />
      </item>
      <item>
        <bioguideId>B001298</bioguideId>
        <fullName>Rep. Bacon, Don [R-NE-2]</fullName>
        <firstName>Don</firstName>
        <middleName />
        <lastName>Bacon</lastName>
        <party>R</party>
        <state>NE</state>
        <identifiers>
          <lisID>2337</lisID>
          <bioguideId>B001298</bioguideId>
          <gpoId />
        </identifiers>
        <district>2</district>
        <sponsorshipDate>2018-02-20</sponsorshipDate>
        <isOriginalCosponsor>True</isOriginalCosponsor>
        <sponsorshipWithdrawnDate />
      </item>
      <item>
        <bioguideId>K000386</bioguideId>
        <fullName>Rep. Katko, John [R-NY-24]</fullName>
        <firstName>John</firstName>
        <middleName />
        <lastName>Katko</lastName>
        <party>R</party>
        <state>NY</state>
        <identifiers>
          <lisID>2264</lisID>
          <bioguideId>K000386</bioguideId>
          <gpoId />
        </identifiers>
        <district>24</district>
        <sponsorshipDate>2018-02-27</sponsorshipDate>
        <isOriginalCosponsor>False</isOriginalCosponsor>
        <sponsorshipWithdrawnDate />
      </item>
      <item>
        <bioguideId>H001077</bioguideId>
        <fullName>Rep. Higgins, Clay [R-LA-3]</fullName>
        <firstName>Clay</firstName>
        <middleName />
        <lastName>Higgins</lastName>
        <party>R</party>
        <state>LA</state>
        <identifiers>
          <lisID>2329</lisID>
          <bioguideId>H001077</bioguideId>
          <gpoId />
        </identifiers>
        <district>3</district>
        <sponsorshipDate>2018-02-27</sponsorshipDate>
        <isOriginalCosponsor>False</isOriginalCosponsor>
        <sponsorshipWithdrawnDate />
      </item>
    </cosponsors>
    <cboCostEstimates>
      <item>
        <pubDate>2018-03-16T12:08:00Z</pubDate>
        <title>H.R. 5074, DHS Cyber Incident Response Teams Act of 2018</title>
        <url>https://www.cbo.gov/publication/53656</url>
      </item>
    </cboCostEstimates>
    <laws />
    <notes />
    <policyArea>
      <name>Science, Technology, Communications</name>
    </policyArea>
    <subjects>
      <billSubjects>
        <legislativeSubjects>
          <item>
            <name>Computer security and identity theft</name>
          </item>
          <item>
            <name>Department of Homeland Security</name>
          </item>
          <item>
            <name>Government studies and investigations</name>
          </item>
          <item>
            <name>Public-private cooperation</name>
          </item>
        </legislativeSubjects>
        <policyArea>
          <name>Science, Technology, Communications</name>
        </policyArea>
      </billSubjects>
    </subjects>
    <summaries>
      <billSummaries>
        <item>
          <versionCode>00</versionCode>
          <actionDate>2018-02-20</actionDate>
          <actionDesc>Introduced in House</actionDesc>
          <lastSummaryUpdateDate>2018-03-19T19:07:30Z</lastSummaryUpdateDate>
          <text><![CDATA[<p><b>DHS Cyber Incident Response Teams Act of 2018</b></p> <p>This bill amends the Homeland Security Act of 2002 to require the Department of Homeland Security's (DHS's) national cybersecurity and communications integration center to maintain cyber hunt and incident response teams to provide, upon request, assistance including: (1) assisting asset owners and operators in restoring services following a cyber incident; (2) identifying cybersecurity risk and unauthorized cyber activity; and (3) mitigation strategies to prevent, deter, and protect against cybersecurity risks.</p> <p>DHS may include private sector cybersecurity specialists on such teams, and must continually assess and evaluate the teams and their operations and report specified metrics to Congress.</p> <p>No additional funds are authorized to carry out this bill.</p>]]></text>
          <updateDate>2018-02-20T05:00:00Z</updateDate>
          <name>Introduced in House</name>
        </item>
        <item>
          <versionCode>36</versionCode>
          <actionDate>2018-03-19</actionDate>
          <actionDesc>Passed House amended</actionDesc>
          <lastSummaryUpdateDate>2018-04-10T19:24:52Z</lastSummaryUpdateDate>
          <text><![CDATA[<p><b>DHS Cyber Incident Response Teams Act of 2018</b></p> <p>(Sec. 2) This bill amends the Homeland Security Act of 2002 to require the Department of Homeland Security's (DHS's) national cybersecurity and communications integration center to maintain cyber hunt and incident response teams to provide, upon request, assistance including: (1) assisting asset owners and operators in restoring services following a cyber incident; (2) identifying cybersecurity risk and unauthorized cyber activity; and (3) mitigation strategies to prevent, deter, and protect against cybersecurity risks.</p> <p>DHS may include private sector cybersecurity specialists on such teams, and must continually assess and evaluate the teams and their operations and report specified metrics to Congress.</p> <p>No additional funds are authorized to carry out this bill.</p>]]></text>
          <updateDate>2018-03-19T13:40:55Z</updateDate>
          <name>Passed House amended</name>
        </item>
      </billSummaries>
    </summaries>
    <title>DHS Cyber Incident Response Teams Act of 2018</title>
    <titles>
      <item>
        <titleType>Official Title as Introduced</titleType>
        <parentTitleType />
        <title>To authorize cyber incident response teams at the Department of Homeland Security, and for other purposes.</title>
        <chamberCode />
        <chamberName />
      </item>
      <item>
        <titleType>Short Titles as Introduced</titleType>
        <parentTitleType />
        <title>DHS Cyber Incident Response Teams Act of 2018</title>
        <chamberCode />
        <chamberName />
      </item>
      <item>
        <titleType>Short Titles as Reported to House</titleType>
        <parentTitleType>Short Titles House of Representatives</parentTitleType>
        <title>DHS Cyber Incident Response Teams Act of 2018</title>
        <chamberCode>H</chamberCode>
        <chamberName>House</chamberName>
      </item>
      <item>
        <titleType>Short Titles as Passed House</titleType>
        <parentTitleType>Short Titles House of Representatives</parentTitleType>
        <title>DHS Cyber Incident Response Teams Act of 2018</title>
        <chamberCode>H</chamberCode>
        <chamberName>House</chamberName>
      </item>
      <item>
        <titleType>Display Title</titleType>
        <parentTitleType />
        <title>DHS Cyber Incident Response Teams Act of 2018</title>
        <chamberCode />
        <chamberName />
      </item>
    </titles>
    <amendments />
    <textVersions>
      <item>
        <type>Referred in Senate</type>
        <date>2018-03-20T04:00:00Z</date>
        <formats>
          <item>
            <url>https://www.govinfo.gov/content/pkg/BILLS-115hr5074rfs/xml/BILLS-115hr5074rfs.xml</url>
          </item>
        </formats>
      </item>
      <item>
        <type>Reported in House</type>
        <date>2018-03-19T04:00:00Z</date>
        <formats>
          <item>
            <url>https://www.govinfo.gov/content/pkg/BILLS-115hr5074rh/xml/BILLS-115hr5074rh.xml</url>
          </item>
        </formats>
      </item>
      <item>
        <type>Engrossed in House</type>
        <date>2018-03-19T04:00:00Z</date>
        <formats>
          <item>
            <url>https://www.govinfo.gov/content/pkg/BILLS-115hr5074eh/xml/BILLS-115hr5074eh.xml</url>
          </item>
        </formats>
      </item>
      <item>
        <type>Introduced in House</type>
        <date>2018-02-20T05:00:00Z</date>
        <formats>
          <item>
            <url>https://www.govinfo.gov/content/pkg/BILLS-115hr5074ih/xml/BILLS-115hr5074ih.xml</url>
          </item>
        </formats>
      </item>
    </textVersions>
    <latestAction>
      <actionDate>2018-03-20</actionDate>
      <text>Received in the Senate and Read twice and referred to the Committee on Homeland Security and Governmental Affairs.</text>
      <links />
    </latestAction>
    <calendarNumbers>
      <item>
        <calendar>U00463</calendar>
        <number />
      </item>
    </calendarNumbers>
    <version>1.0.0</version>
  </bill>
  <dublinCore xmlns:dc="http://purl.org/dc/elements/1.1/">
    <dc:format>text/xml</dc:format>
    <dc:language>EN</dc:language>
    <dc:rights>Pursuant to Title 17 Section 105 of the United States Code, this file is not subject to copyright protection and is in the public domain.</dc:rights>
    <dc:contributor>Congressional Research Service, Library of Congress</dc:contributor>
    <dc:description>This file contains bill summaries and statuses for federal legislation. A bill summary describes the most significant provisions of a piece of legislation and details the effects the legislative text may have on current law and federal programs. Bill summaries are authored by the Congressional Research Service (CRS) of the Library of Congress. As stated in Public Law 91-510 (2 USC 166 (d)(6)), one of the duties of CRS is "to prepare summaries and digests of bills and resolutions of a public general nature introduced in the Senate or House of Representatives". For more information, refer to the User Guide that accompanies this file.</dc:description>
  </dublinCore>
</billStatus>

