<?xml version="1.0" encoding="UTF-8"?>
<billStatus>
  <bill>
    <billNumber>6438</billNumber>
    <createDate>2018-07-20T07:10:45Z</createDate>
    <updateDate>2021-07-10T20:11:22Z</updateDate>
    <originChamber>House</originChamber>
    <billType>HR</billType>
    <introducedDate>2018-07-19</introducedDate>
    <congress>115</congress>
    <constitutionalAuthorityStatementText><![CDATA[<pre>[Congressional Record Volume 164, Number 122 (Thursday, July 19, 2018)]From the Congressional Record Online through the Government Publishing Office [<a href='http://www.gpo.gov'>www.gpo.gov</a>]By Mr. PERRY:H.R. 6438.Congress has the power to enact this legislation pursuantto the following:Article 1, Section 8, Clause 18--To make all Laws whichshall be necessary and proper for carrying into Execution theforegoing Powers, and all other Powers vested by thisConstitution in the Government of the United States or in anyDepartment or Officer thereof.[Page H6588]</pre>]]></constitutionalAuthorityStatementText>
    <recordedVotes />
    <committees>
      <billCommittees>
        <item>
          <systemCode>ssga00</systemCode>
          <name>Homeland Security and Governmental Affairs Committee</name>
          <chamber>Senate</chamber>
          <type>Standing</type>
          <subcommittees />
          <activities>
            <item>
              <name>Referred to</name>
              <date>2018-09-05T17:17:59Z</date>
            </item>
          </activities>
        </item>
        <item>
          <systemCode>hshm00</systemCode>
          <name>Homeland Security Committee</name>
          <chamber>House</chamber>
          <type>Standing</type>
          <subcommittees />
          <activities>
            <item>
              <name>Reported by</name>
              <date>2018-08-28T17:37:51Z</date>
            </item>
            <item>
              <name>Markup by</name>
              <date>2018-07-24T17:16:30Z</date>
            </item>
            <item>
              <name>Referred to</name>
              <date>2018-07-19T13:02:20Z</date>
            </item>
          </activities>
        </item>
      </billCommittees>
    </committees>
    <committeeReports>
      <committeeReport>
        <citation>H. Rept. 115-908</citation>
      </committeeReport>
    </committeeReports>
    <relatedBills />
    <actions>
      <item>
        <actionDate>2018-09-05</actionDate>
        <committees>
          <item>
            <systemCode>ssga00</systemCode>
            <name>Homeland Security and Governmental Affairs Committee</name>
          </item>
        </committees>
        <links />
        <sourceSystem>
          <code>0</code>
          <name>Senate</name>
        </sourceSystem>
        <text>Received in the Senate and Read twice and referred to the Committee on Homeland Security and Governmental Affairs.</text>
        <type>IntroReferral</type>
      </item>
      <item>
        <actionDate>2018-09-04</actionDate>
        <actionTime>19:34:30</actionTime>
        <links />
        <text>Motion to reconsider laid on the table Agreed to without objection.</text>
        <type>Floor</type>
        <actionCode>H38310</actionCode>
        <sourceSystem>
          <code>2</code>
          <name>House floor actions</name>
        </sourceSystem>
        <committees />
      </item>
      <item>
        <actionDate>2018-09-04</actionDate>
        <actionTime>19:34:29</actionTime>
        <links />
        <text>On motion to suspend the rules and pass the bill, as amended Agreed to by voice vote. (text: CR H7810)</text>
        <type>Floor</type>
        <actionCode>H37300</actionCode>
        <sourceSystem>
          <code>2</code>
          <name>House floor actions</name>
        </sourceSystem>
        <committees />
      </item>
      <item>
        <actionDate>2018-09-04</actionDate>
        <actionTime>19:34:29</actionTime>
        <links />
        <text>Passed/agreed to in House: On motion to suspend the rules and pass the bill, as amended Agreed to by voice vote.(text: CR H7810)</text>
        <type>Floor</type>
        <actionCode>8000</actionCode>
        <sourceSystem>
          <code>9</code>
          <name>Library of Congress</name>
        </sourceSystem>
        <committees />
      </item>
      <item>
        <actionDate>2018-09-04</actionDate>
        <actionTime>19:26:26</actionTime>
        <links />
        <text>DEBATE - The House proceeded with forty minutes of debate on H.R. 6438.</text>
        <type>Floor</type>
        <actionCode>H8D000</actionCode>
        <sourceSystem>
          <code>2</code>
          <name>House floor actions</name>
        </sourceSystem>
        <committees />
      </item>
      <item>
        <actionDate>2018-09-04</actionDate>
        <actionTime>19:26:25</actionTime>
        <links />
        <text>Considered under suspension of the rules. (consideration: CR S7810-7811)</text>
        <type>Floor</type>
        <actionCode>H30000</actionCode>
        <sourceSystem>
          <code>2</code>
          <name>House floor actions</name>
        </sourceSystem>
        <committees />
      </item>
      <item>
        <actionDate>2018-09-04</actionDate>
        <actionTime>19:26:04</actionTime>
        <links />
        <text>Mr. Perry moved to suspend the rules and pass the bill, as amended.</text>
        <type>Floor</type>
        <actionCode>H30300</actionCode>
        <sourceSystem>
          <code>2</code>
          <name>House floor actions</name>
        </sourceSystem>
        <committees />
      </item>
      <item>
        <actionDate>2018-08-28</actionDate>
        <links />
        <text>Placed on the Union Calendar, Calendar No. 704.</text>
        <type>Calendars</type>
        <actionCode>H12410</actionCode>
        <sourceSystem>
          <code>2</code>
          <name>House floor actions</name>
        </sourceSystem>
        <committees />
      </item>
      <item>
        <actionDate>2018-08-28</actionDate>
        <links />
        <text>Reported by the Committee on Homeland Security. H. Rept. 115-908.</text>
        <type>Committee</type>
        <actionCode>H12200</actionCode>
        <sourceSystem>
          <code>2</code>
          <name>House floor actions</name>
        </sourceSystem>
        <committees>
          <item>
            <systemCode>hshm00</systemCode>
            <name>Homeland Security Committee</name>
          </item>
        </committees>
      </item>
      <item>
        <actionDate>2018-08-28</actionDate>
        <links />
        <text>Reported by the Committee on Homeland Security. H. Rept. 115-908.</text>
        <type>Committee</type>
        <actionCode>5000</actionCode>
        <sourceSystem>
          <code>9</code>
          <name>Library of Congress</name>
        </sourceSystem>
        <committees>
          <item>
            <systemCode>hshm00</systemCode>
            <name>Homeland Security Committee</name>
          </item>
        </committees>
      </item>
      <item>
        <actionDate>2018-07-24</actionDate>
        <committees>
          <item>
            <systemCode>hshm00</systemCode>
            <name>Homeland Security Committee</name>
          </item>
        </committees>
        <links />
        <sourceSystem>
          <code>1</code>
          <name>House committee actions</name>
        </sourceSystem>
        <text>Ordered to be Reported by Unanimous Consent.</text>
        <type>Committee</type>
      </item>
      <item>
        <actionDate>2018-07-24</actionDate>
        <committees>
          <item>
            <systemCode>hshm00</systemCode>
            <name>Homeland Security Committee</name>
          </item>
        </committees>
        <links />
        <sourceSystem>
          <code>1</code>
          <name>House committee actions</name>
        </sourceSystem>
        <text>Committee Consideration and Mark-up Session Held.</text>
        <type>Committee</type>
      </item>
      <item>
        <actionDate>2018-07-19</actionDate>
        <links />
        <text>Referred to the House Committee on Homeland Security.</text>
        <type>IntroReferral</type>
        <actionCode>H11100</actionCode>
        <sourceSystem>
          <code>2</code>
          <name>House floor actions</name>
        </sourceSystem>
        <committees>
          <item>
            <systemCode>hshm00</systemCode>
            <name>Homeland Security Committee</name>
          </item>
        </committees>
      </item>
      <item>
        <actionDate>2018-07-19</actionDate>
        <links />
        <text>Introduced in House</text>
        <type>IntroReferral</type>
        <actionCode>Intro-H</actionCode>
        <sourceSystem>
          <code>9</code>
          <name>Library of Congress</name>
        </sourceSystem>
        <committees />
      </item>
      <item>
        <actionDate>2018-07-19</actionDate>
        <links />
        <text>Introduced in House</text>
        <type>IntroReferral</type>
        <actionCode>1000</actionCode>
        <sourceSystem>
          <code>9</code>
          <name>Library of Congress</name>
        </sourceSystem>
        <committees />
      </item>
      <actionTypeCounts>
        <referredToCommittee>1</referredToCommittee>
        <motionToReconsiderResults>1</motionToReconsiderResults>
        <finalPassageUnderSuspensionOfTheRulesResults>1</finalPassageUnderSuspensionOfTheRulesResults>
        <passedAgreedToInHouse>1</passedAgreedToInHouse>
        <generalDebate>1</generalDebate>
        <considerationByHouse>1</considerationByHouse>
        <motionMadeToSuspendTheRules>1</motionMadeToSuspendTheRules>
        <unionCalendarAssignment>1</unionCalendarAssignment>
        <committeeReportOfABill>1</committeeReportOfABill>
        <reportedToHouse>1</reportedToHouse>
        <orderedToBeReported>1</orderedToBeReported>
        <committeeConsiderationMarkUp>1</committeeConsiderationMarkUp>
        <billReferrals>1</billReferrals>
        <introducedInTheHouse>1</introducedInTheHouse>
        <introducedInHouse>1</introducedInHouse>
      </actionTypeCounts>
      <actionByCounts>
        <senate>1</senate>
        <houseOfRepresentatives>14</houseOfRepresentatives>
      </actionByCounts>
    </actions>
    <sponsors>
      <item>
        <bioguideId>P000605</bioguideId>
        <fullName>Rep. Perry, Scott [R-PA-4]</fullName>
        <firstName>Scott</firstName>
        <middleName />
        <lastName>Perry</lastName>
        <party>R</party>
        <state>PA</state>
        <identifiers>
          <lisID>2157</lisID>
          <bioguideId>P000605</bioguideId>
          <gpoId />
        </identifiers>
        <district>4</district>
        <byRequestType />
      </item>
    </sponsors>
    <cosponsors>
      <item>
        <bioguideId>M001157</bioguideId>
        <fullName>Rep. McCaul, Michael T. [R-TX-10]</fullName>
        <firstName>Michael</firstName>
        <middleName>T.</middleName>
        <lastName>McCaul</lastName>
        <party>R</party>
        <state>TX</state>
        <identifiers>
          <lisID>1804</lisID>
          <bioguideId>M001157</bioguideId>
          <gpoId>8166</gpoId>
        </identifiers>
        <district>10</district>
        <sponsorshipDate>2018-07-19</sponsorshipDate>
        <isOriginalCosponsor>True</isOriginalCosponsor>
        <sponsorshipWithdrawnDate />
      </item>
    </cosponsors>
    <cboCostEstimates>
      <item>
        <pubDate>2018-08-07T18:45:25Z</pubDate>
        <title>H.R. 6438, DHS Countering Unmanned Aircraft Systems Coordinator Act</title>
        <url>https://www.cbo.gov/publication/54346</url>
      </item>
    </cboCostEstimates>
    <laws />
    <notes />
    <policyArea>
      <name>Emergency Management</name>
    </policyArea>
    <subjects>
      <billSubjects>
        <legislativeSubjects>
          <item>
            <name>Aviation and airports</name>
          </item>
          <item>
            <name>Department of Homeland Security</name>
          </item>
          <item>
            <name>Executive agency funding and structure</name>
          </item>
          <item>
            <name>Federal officials</name>
          </item>
          <item>
            <name>Federal-Indian relations</name>
          </item>
          <item>
            <name>Intergovernmental relations</name>
          </item>
          <item>
            <name>Public-private cooperation</name>
          </item>
          <item>
            <name>Research and development</name>
          </item>
          <item>
            <name>State and local government operations</name>
          </item>
          <item>
            <name>Terrorism</name>
          </item>
          <item>
            <name>Transportation safety and security</name>
          </item>
        </legislativeSubjects>
        <policyArea>
          <name>Emergency Management</name>
        </policyArea>
      </billSubjects>
    </subjects>
    <summaries>
      <billSummaries>
        <item>
          <versionCode>00</versionCode>
          <actionDate>2018-07-19</actionDate>
          <actionDesc>Introduced in House</actionDesc>
          <lastSummaryUpdateDate>2018-09-11T16:57:03Z</lastSummaryUpdateDate>
          <text><![CDATA[<p><b>DHS Countering Unmanned Aircraft Systems Coordinator Act</b></p> <p>This bill amends the Homeland Security Act of 2002 to direct the Department of Homeland Security (DHS) to designate a DHS official as the Countering Unmanned Aircraft Systems (UAS) Coordinator to coordinate with relevant DHS offices and components on the development of policies and plans to counter threats associated with UAS, including the possible use of UAS in a terrorist attack.</p> <p>The coordinator shall: (1) ensure that activities for identifying, assessing, or defeating a UAS are carried out in accordance with applicable federal laws; and (2) serve as the principal DHS official for disseminating information regarding counter-UAS technology to the private sector.</p>]]></text>
          <updateDate>2018-07-19T04:00:00Z</updateDate>
          <name>Introduced in House</name>
        </item>
        <item>
          <versionCode>79</versionCode>
          <actionDate>2018-08-28</actionDate>
          <actionDesc>Reported to House without amendment</actionDesc>
          <lastSummaryUpdateDate>2018-09-11T16:59:05Z</lastSummaryUpdateDate>
          <text><![CDATA[<p><b>DHS Countering Unmanned Aircraft Systems Coordinator Act</b></p> <p>This bill amends the Homeland Security Act of 2002 to direct the Department of Homeland Security (DHS) to designate a DHS official as the Countering Unmanned Aircraft Systems (UAS) Coordinator to coordinate with relevant DHS offices and components on the development of policies and plans to counter threats associated with UAS, including the possible use of UAS in a terrorist attack.</p> <p>The coordinator shall: (1) ensure that activities for identifying, assessing, or defeating a UAS are carried out in accordance with applicable federal laws; and (2) serve as the principal DHS official for disseminating information regarding counter-UAS technology to the private sector.</p>]]></text>
          <updateDate>2018-08-28T14:29:50Z</updateDate>
          <name>Reported to House without amendment</name>
        </item>
        <item>
          <versionCode>36</versionCode>
          <actionDate>2018-09-04</actionDate>
          <actionDesc>Passed House amended</actionDesc>
          <lastSummaryUpdateDate>2018-09-11T16:25:41Z</lastSummaryUpdateDate>
          <text><![CDATA[<p><b>DHS Countering Unmanned Aircraft Systems Coordinator Act</b></p> <p>(Sec. 2) This bill amends the Homeland Security Act of 2002 to direct the Department of Homeland Security (DHS) to designate a DHS official as the Countering Unmanned Aircraft Systems (UAS) Coordinator to coordinate with relevant DHS offices and components on the development of policies and plans to counter threats associated with UAS, including:</p> <ul> <li> countering UAS that may be used in a terrorist attack; </li> <li> promoting research and development of counter UAS technologies; </li> <li> ensuring the dissemination of information and guidance related to countering such threats; and</li> <li> serving as the DHS point of contact for federal, state, local, and tribal law enforcement entities and the private sector regarding DHS activities to counter UAS.</li> </ul> <p>The coordinator shall: (1) ensure that activities for identifying, assessing, or defeating a UAS are carried out in accordance with applicable federal laws; and (2) serve as the principal DHS official for disseminating information regarding counter-UAS technology to the private sector.</p>]]></text>
          <updateDate>2018-09-04T13:20:23Z</updateDate>
          <name>Passed House amended</name>
        </item>
      </billSummaries>
    </summaries>
    <title>DHS Countering Unmanned Aircraft Systems Coordinator Act</title>
    <titles>
      <item>
        <titleType>Official Title as Introduced</titleType>
        <parentTitleType />
        <title>To amend the Homeland Security Act of 2002 to establish in the Department of Homeland Security an Unmanned Aircraft Systems Coordinator, and for other purposes.</title>
        <chamberCode />
        <chamberName />
      </item>
      <item>
        <titleType>Short Titles as Introduced</titleType>
        <parentTitleType />
        <title>DHS Countering Unmanned Aircraft Systems Coordinator Act</title>
        <chamberCode />
        <chamberName />
      </item>
      <item>
        <titleType>Short Titles as Reported to House</titleType>
        <parentTitleType>Short Titles House of Representatives</parentTitleType>
        <title>DHS Countering Unmanned Aircraft Systems Coordinator Act</title>
        <chamberCode>H</chamberCode>
        <chamberName>House</chamberName>
      </item>
      <item>
        <titleType>Short Titles as Passed House</titleType>
        <parentTitleType>Short Titles House of Representatives</parentTitleType>
        <title>DHS Countering Unmanned Aircraft Systems Coordinator Act</title>
        <chamberCode>H</chamberCode>
        <chamberName>House</chamberName>
      </item>
      <item>
        <titleType>Display Title</titleType>
        <parentTitleType />
        <title>DHS Countering Unmanned Aircraft Systems Coordinator Act</title>
        <chamberCode />
        <chamberName />
      </item>
    </titles>
    <amendments />
    <textVersions>
      <item>
        <type>Referred in Senate</type>
        <date>2018-09-05T04:00:00Z</date>
        <formats>
          <item>
            <url>https://www.govinfo.gov/content/pkg/BILLS-115hr6438rfs/xml/BILLS-115hr6438rfs.xml</url>
          </item>
        </formats>
      </item>
      <item>
        <type>Engrossed in House</type>
        <date>2018-09-04T04:00:00Z</date>
        <formats>
          <item>
            <url>https://www.govinfo.gov/content/pkg/BILLS-115hr6438eh/xml/BILLS-115hr6438eh.xml</url>
          </item>
        </formats>
      </item>
      <item>
        <type>Reported in House</type>
        <date>2018-08-28T04:00:00Z</date>
        <formats>
          <item>
            <url>https://www.govinfo.gov/content/pkg/BILLS-115hr6438rh/xml/BILLS-115hr6438rh.xml</url>
          </item>
        </formats>
      </item>
      <item>
        <type>Introduced in House</type>
        <date>2018-07-19T04:00:00Z</date>
        <formats>
          <item>
            <url>https://www.govinfo.gov/content/pkg/BILLS-115hr6438ih/xml/BILLS-115hr6438ih.xml</url>
          </item>
        </formats>
      </item>
    </textVersions>
    <latestAction>
      <actionDate>2018-09-05</actionDate>
      <text>Received in the Senate and Read twice and referred to the Committee on Homeland Security and Governmental Affairs.</text>
      <links />
    </latestAction>
    <calendarNumbers>
      <item>
        <calendar>U00704</calendar>
        <number />
      </item>
    </calendarNumbers>
    <version>1.0.0</version>
  </bill>
  <dublinCore xmlns:dc="http://purl.org/dc/elements/1.1/">
    <dc:format>text/xml</dc:format>
    <dc:language>EN</dc:language>
    <dc:rights>Pursuant to Title 17 Section 105 of the United States Code, this file is not subject to copyright protection and is in the public domain.</dc:rights>
    <dc:contributor>Congressional Research Service, Library of Congress</dc:contributor>
    <dc:description>This file contains bill summaries and statuses for federal legislation. A bill summary describes the most significant provisions of a piece of legislation and details the effects the legislative text may have on current law and federal programs. Bill summaries are authored by the Congressional Research Service (CRS) of the Library of Congress. As stated in Public Law 91-510 (2 USC 166 (d)(6)), one of the duties of CRS is "to prepare summaries and digests of bills and resolutions of a public general nature introduced in the Senate or House of Representatives". For more information, refer to the User Guide that accompanies this file.</dc:description>
  </dublinCore>
</billStatus>

